vkchatbot/__init__.py
vkchatbot/objects.py
VKChatBot-0.0.1.dist-info/METADATA
VKChatBot-0.0.1.dist-info/WHEEL
VKChatBot-0.0.1.dist-info/top_level.txt
VKChatBot-0.0.1.dist-info/RECORD
