Metadata-Version: 2.1
Name: VKChatBot
Version: 0.0.1
Summary: Library for easy creating of chat bots for VK.com
Home-page: https://github.com/PashaWNN/vkchatbot/
Author: Pavel Shishmarev
Author-email: pashawnn@gmail.com
License: UNKNOWN
Platform: UNKNOWN
Classifier: Programming Language :: Python :: 3
Classifier: Operating System :: OS Independent
Requires-Python: >=3.5, <4
Requires-Dist: requests
